karrio/mappers/veho/__init__.py
karrio/mappers/veho/mapper.py
karrio/mappers/veho/proxy.py
karrio/mappers/veho/settings.py
karrio/plugins/veho/__init__.py
karrio/providers/veho/__init__.py
karrio/providers/veho/error.py
karrio/providers/veho/rate.py
karrio/providers/veho/tracking.py
karrio/providers/veho/units.py
karrio/providers/veho/utils.py
karrio/providers/veho/shipment/__init__.py
karrio/providers/veho/shipment/cancel.py
karrio/providers/veho/shipment/create.py
karrio/schemas/veho/__init__.py
karrio/schemas/veho/error_response.py
karrio/schemas/veho/rate_request.py
karrio/schemas/veho/rate_response.py
karrio/schemas/veho/shipment_cancel_request.py
karrio/schemas/veho/shipment_cancel_response.py
karrio/schemas/veho/shipment_request.py
karrio/schemas/veho/shipment_response.py
karrio/schemas/veho/tracking_request.py
karrio/schemas/veho/tracking_response.py
karrio_veho-2026.1.4.dist-info/METADATA
karrio_veho-2026.1.4.dist-info/WHEEL
karrio_veho-2026.1.4.dist-info/entry_points.txt
karrio_veho-2026.1.4.dist-info/top_level.txt
karrio_veho-2026.1.4.dist-info/RECORD
